{
  "test_data": [
    [
      [
        -0.9005247206054353,
        0.07964415848255157,
        -1.1318742036819458,
        -0.730324387550354,
        0.08465699106454849,
        -0.6751041412353516,
        0.6228264570236206,
        -1.1435719338903103,
        0.0
      ]
    ]
  ],
  "cfs_list": [
    [
      [
        -0.9005247206054353,
        1.36561598,
        -1.131874150865373,
        -0.7303243622009813,
        0.0846569896139694,
        0.18413232,
        0.6228264467724509,
        -1.1435719338903103,
        1.0
      ],
      [
        -0.9005247206054353,
        1.62448669,
        -1.131874150865373,
        -0.7303243622009813,
        0.0846569896139694,
        1.41836273,
        0.6228264467724509,
        -1.1435719338903103,
        1.0
      ],
      [
        -0.9005247206054353,
        1.28614658,
        -1.131874150865373,
        -0.7303243622009813,
        0.0846569896139694,
        1.58462441,
        0.6228264467724509,
        -1.1435719338903103,
        1.0
      ],
      [
        -0.9005247206054353,
        1.48538599,
        -1.131874150865373,
        -0.7303243622009813,
        0.0846569896139694,
        1.22516758,
        0.6228264467724509,
        -1.1435719338903103,
        1.0
      ],
      [
        -0.9005247206054353,
        1.34164318,
        -1.131874150865373,
        -0.7303243622009813,
        0.0846569896139694,
        1.35240858,
        0.6228264467724509,
        -1.1435719338903103,
        1.0
      ]
    ]
  ],
  "local_importance": null,
  "summary_importance": null,
  "data_interface": {
    "outcome_name": "Outcome",
    "data_df": "dummy_data"
  },
  "feature_names": [
    "Pregnancies",
    "Glucose",
    "BloodPressure",
    "SkinThickness",
    "Insulin",
    "BMI",
    "DiabetesPedigreeFunction",
    "Age"
  ],
  "feature_names_including_target": [
    "Pregnancies",
    "Glucose",
    "BloodPressure",
    "SkinThickness",
    "Insulin",
    "BMI",
    "DiabetesPedigreeFunction",
    "Age",
    "Outcome"
  ],
  "model_type": "classifier",
  "desired_class": 1,
  "desired_range": null,
  "metadata": {
    "model_name": "Random Forest",
    "patient_idx": 1,
    "dice_method_used": "random",
    "actionable_features": [
      "Glucose",
      "BMI",
      "BloodPressure",
      "Insulin"
    ],
    "permitted_range_quantiles": [
      0.05,
      0.95
    ]
  }
}