{
  "test_data": [
    [
      [
        2.8640080364698703,
        0.9467164278030396,
        1.098129153251648,
        0.7832227349281311,
        -0.4569171965122223,
        -0.6589533686637878,
        0.8130154609680176,
        0.8104950509596776,
        1.0
      ]
    ]
  ],
  "cfs_list": [
    [
      [
        2.8640080364698703,
        -1.2455486,
        0.6918779,
        0.7832227,
        -0.2824506,
        -1.0126665,
        0.8130155,
        0.8104950509596776,
        0.0
      ],
      [
        2.8640080364698703,
        -1.2455486,
        0.6918779,
        0.7832227,
        -0.6521447,
        -1.0126665,
        0.8130155,
        0.8104950509596776,
        0.0
      ],
      [
        2.8640080364698703,
        -1.3218098,
        0.6918779,
        0.7832227,
        -0.6521447,
        -1.0126665,
        0.8130155,
        0.8104950509596776,
        0.0
      ],
      [
        2.8640080364698703,
        -1.3218098,
        0.6918779,
        0.7832227,
        -0.7221696,
        -0.9210184,
        0.8130155,
        0.8104950509596776,
        0.0
      ],
      [
        2.8640080364698703,
        -1.2455486,
        0.6918779,
        0.7832227,
        -0.0087322,
        -0.46512964,
        0.8130155,
        0.8104950509596776,
        0.0
      ]
    ]
  ],
  "local_importance": null,
  "summary_importance": null,
  "data_interface": {
    "outcome_name": "outcome",
    "data_df": "dummy_data"
  },
  "feature_names": [
    "pregnancies",
    "glucose",
    "bloodpressure",
    "skinthickness",
    "insulin",
    "bmi",
    "diabetespedigreefunction",
    "age"
  ],
  "feature_names_including_target": [
    "pregnancies",
    "glucose",
    "bloodpressure",
    "skinthickness",
    "insulin",
    "bmi",
    "diabetespedigreefunction",
    "age",
    "outcome"
  ],
  "model_type": "classifier",
  "desired_class": 0.0,
  "desired_range": null,
  "metadata": {
    "model_name": "Multi-Layer Perceptron",
    "patient_idx": 3,
    "dice_method_used": "genetic",
    "actionable_features": [
      "glucose",
      "bmi",
      "bloodpressure",
      "insulin"
    ],
    "permitted_range_quantiles": [
      0.05,
      0.95
    ]
  }
}